flake8_async/__init__.py
flake8_async/__main__.py
flake8_async/base.py
flake8_async/runner.py
flake8_async/visitors/__init__.py
flake8_async/visitors/flake8asyncvisitor.py
flake8_async/visitors/helpers.py
flake8_async/visitors/visitor101.py
flake8_async/visitors/visitor102_120.py
flake8_async/visitors/visitor103_104.py
flake8_async/visitors/visitor105.py
flake8_async/visitors/visitor111.py
flake8_async/visitors/visitor118.py
flake8_async/visitors/visitor123.py
flake8_async/visitors/visitor2xx.py
flake8_async/visitors/visitor4xx.py
flake8_async/visitors/visitor91x.py
flake8_async/visitors/visitor_utility.py
flake8_async/visitors/visitors.py
flake8_async-25.7.1.dist-info/METADATA
flake8_async-25.7.1.dist-info/WHEEL
flake8_async-25.7.1.dist-info/entry_points.txt
flake8_async-25.7.1.dist-info/top_level.txt
flake8_async-25.7.1.dist-info/RECORD
