Metadata-Version: 2.4
Name: flake8-async
Version: 25.7.1
Summary: A highly opinionated flake8 plugin for Trio-related problems.
Author: Zac Hatfield-Dodds, John Litborn, and Contributors
Author-email: zac@zhd.dev
License: MIT
Project-URL: Homepage, https://github.com/python-trio/flake8-async
Project-URL: Documentation, https://flake8-async.readthedocs.io/
Project-URL: Changelog, https://flake8-async.readthedocs.io/en/latest/changelog.html
Classifier: Development Status :: 3 - Alpha
Classifier: Framework :: Flake8
Classifier: Intended Audience :: Developers
Classifier: License :: OSI Approved :: MIT License
Classifier: Programming Language :: Python
Classifier: Programming Language :: Python :: 3
Classifier: Programming Language :: Python :: 3.9
Classifier: Programming Language :: Python :: 3.10
Classifier: Programming Language :: Python :: 3.11
Classifier: Programming Language :: Python :: 3.12
Classifier: Programming Language :: Python :: 3.13
Requires-Python: >=3.9
Requires-Dist: libcst>=1.0.1
Provides-Extra: flake8
Requires-Dist: flake8>=6; extra == "flake8"
Dynamic: author
Dynamic: author-email
Dynamic: classifier
Dynamic: description
Dynamic: description-content-type
Dynamic: license
Dynamic: project-url
Dynamic: provides-extra
Dynamic: requires-dist
Dynamic: requires-python
Dynamic: summary
